README.md
setup.py
covid19_full_stat/__init__.py
covid19_full_stat/aditional_f.py
covid19_full_stat/covid19.py
covid19_full_stat.egg-info/PKG-INFO
covid19_full_stat.egg-info/SOURCES.txt
covid19_full_stat.egg-info/dependency_links.txt
covid19_full_stat.egg-info/requires.txt
covid19_full_stat.egg-info/top_level.txt