Metadata-Version: 1.0
Name: covid19-full-stat
Version: 0.0.2.4
Summary: Сovid19 statistics per countries and for the world
Home-page: https://github.com/Sergii-Lak/covid19-info-stats
Author: Sergii-Lak
Author-email: serg1509@yandex.ru
License: MIT
Platform: UNKNOWN
